subsql/__init__.py
subsql/sqlitedriver.py
subsql/subsql.py
subsql/driver/__init__.py
subsql/driver/sqlite.py
subsql/parser/__init__.py
subsql/parser/parser.py
subsql/parser/types.py
subsql/parser/util.py
subsql-0.0.1.dist-info/METADATA
subsql-0.0.1.dist-info/WHEEL
subsql-0.0.1.dist-info/top_level.txt
subsql-0.0.1.dist-info/RECORD
