Metadata-Version: 2.1
Name: subsql
Version: 0.0.1
Summary: Store SQL queries in files
Home-page: https://github.com/pshangov/subsql-py
Author: Peter Shangov
Author-email: pshangov@yahoo.com
License: MIT
Project-URL: Bug Tracker, https://github.com/pshangov/subsql-py/issues
Platform: UNKNOWN
Classifier: Programming Language :: Python :: 3
Classifier: License :: OSI Approved :: MIT License
Classifier: Operating System :: OS Independent
Requires-Python: >=3.7
